odoo/addons/sale_order_line_temporary_price/LICENSE
odoo/addons/sale_order_line_temporary_price/README.rst
odoo/addons/sale_order_line_temporary_price/__init__.py
odoo/addons/sale_order_line_temporary_price/__manifest__.py
odoo/addons/sale_order_line_temporary_price/i18n/de_CH.po
odoo/addons/sale_order_line_temporary_price/images/screen.png
odoo/addons/sale_order_line_temporary_price/models/__init__.py
odoo/addons/sale_order_line_temporary_price/models/sale_order_line.py
odoo/addons/sale_order_line_temporary_price/static/description/icon.png
odoo/addons/sale_order_line_temporary_price/static/description/index.html
odoo/addons/sale_order_line_temporary_price/views/sale_order.xml
odoo/addons/sale_order_line_temporary_price/wizards/__init__.py
odoo/addons/sale_order_line_temporary_price/wizards/sale_make_invoice_advance.py
odoo_addon_sale_order_line_temporary_price-16.0.1.0.0.dist-info/METADATA
odoo_addon_sale_order_line_temporary_price-16.0.1.0.0.dist-info/WHEEL
odoo_addon_sale_order_line_temporary_price-16.0.1.0.0.dist-info/top_level.txt
odoo_addon_sale_order_line_temporary_price-16.0.1.0.0.dist-info/RECORD
